ome2xarray/__init__.py
ome2xarray/companion.py
ome2xarray-0.3.1.dist-info/METADATA
ome2xarray-0.3.1.dist-info/WHEEL
ome2xarray-0.3.1.dist-info/licenses/LICENSE
ome2xarray-0.3.1.dist-info/RECORD
