Metadata-Version: 2.4
Name: ome2xarray
Version: 0.3.1
Author-email: Jan Eglinger <jan.eglinger@fmi.ch>
License-Expression: BSD-3-Clause
License-File: LICENSE
Requires-Python: >=3.11
Requires-Dist: dask>=2025.7.0
Requires-Dist: ome-types<0.7,>=0.6.1
Requires-Dist: tifffile>=2024.12.12
Requires-Dist: xarray>=2025.9.0
